mpypip/__about__.py
mpypip/__init__.py
mpypip/cli.py
mpypip/create.py
mpypip/pypip.py
mpypip-0.0.15.dist-info/METADATA
mpypip-0.0.15.dist-info/WHEEL
mpypip-0.0.15.dist-info/entry_points.txt
mpypip-0.0.15.dist-info/licenses/LICENSE
mpypip-0.0.15.dist-info/RECORD
