Metadata-Version: 2.3
Name: mpypip
Version: 0.0.15
Summary: Install and manage pyproject.toml with pip commands.
Project-URL: Documentation, https://github.com/mbodiai/mpypip#readme
Project-URL: Issues, https://github.com/mbodiai/mpypip/issues
Project-URL: Source, https://github.com/mbodiai/mpypip
Author-email: Sebastian Peralta <sebastian@mbodi.ai>
License-Expression: Apache-2.0
License-File: LICENSE
Classifier: Development Status :: 4 - Beta
Classifier: Programming Language :: Python
Classifier: Programming Language :: Python :: 3.8
Classifier: Programming Language :: Python :: 3.9
Classifier: Programming Language :: Python :: 3.10
Classifier: Programming Language :: Python :: 3.11
Classifier: Programming Language :: Python :: 3.12
Classifier: Programming Language :: Python :: Implementation :: CPython
Classifier: Programming Language :: Python :: Implementation :: PyPy
Requires-Python: >=3.8
Requires-Dist: click==8.1.7
Requires-Dist: mrender
Requires-Dist: packaging==24.1
Requires-Dist: requests==2.32.3
Requires-Dist: rich==13.7.1
Requires-Dist: toml==0.10.2
Requires-Dist: tomlkit==0.13.0
